tile_downloader/__init__.py
tile_downloader/downloader.py
tile_downloader-1.0.0.dist-info/licenses/LICENSE
tile_downloader_gui/TileDownloaderGUI.py
tile_downloader_gui/__init__.py
tile_downloader-1.0.0.dist-info/METADATA
tile_downloader-1.0.0.dist-info/WHEEL
tile_downloader-1.0.0.dist-info/entry_points.txt
tile_downloader-1.0.0.dist-info/top_level.txt
tile_downloader-1.0.0.dist-info/RECORD
