Metadata-Version: 2.4
Name: tile_downloader
Version: 1.0.0
Summary: A utility for downloading map tiles from various providers based on geographic boundaries.
Home-page: https://github.com/A-Talebifard/tile-downloader
Author: Abbas Talebifard
Author-email: Abbastalebifard@gmail.com
License: MIT
Classifier: Programming Language :: Python :: 3
Classifier: License :: OSI Approved :: MIT License
Classifier: Operating System :: OS Independent
Classifier: Topic :: Scientific/Engineering :: GIS
Classifier: Topic :: Utilities
Requires-Python: >=3.7
License-File: LICENSE
Requires-Dist: requests
Requires-Dist: Pillow
Requires-Dist: tqdm
Requires-Dist: shapely
Requires-Dist: pyproj
Requires-Dist: pmtiles
Dynamic: author
Dynamic: author-email
Dynamic: classifier
Dynamic: description
Dynamic: description-content-type
Dynamic: home-page
Dynamic: license
Dynamic: license-file
Dynamic: requires-dist
Dynamic: requires-python
Dynamic: summary
